[
  {
    "name": "EVENTOS",
    "samples": [
      {
        "name": "EVENTO GOTI 1",
        "uri" : "https://vkvsd213.mycdn.me/hls/4482616527559.m3u8/sig/xwMC3kod1OU/expires/1684182410803/srcIp/201.218.157.2/urls/45.136.22.53/clientType/13/srcAg/CHROME_ANDROID/mid/5181807733703/4482616527559_high/index.m3u8"
      },
      {
        "name": "EVENTO GOTI 2",
        "uri": "https://www.mediaserver.express/live//hh359oau/index.m3u8"
      },
      {
        "name": "EVENTO GOTI 3",
        "uri": "https://cdnhd.iblups.com/hls/TxIRX36Ndx.m3u8"
      },
      {
        "name": "EVENTO GOTI 4",
        "uri": "https://b7i4j3n3.stackpathcdn.com/dlive-mdpaiykokj/1684097988/src/live.m3u8"
      }
    ]
  },
  {
    "name": "CULTURA",
    "samples": [
      {
        "name": "HISTORY",
        "uri": "https://edge-live16-sl.cvattv.com.ar/live/c7eds/HistoryHD/SA_Live_dash_enc_2A/HistoryHD.mpd",
        "drm_scheme": "clearkey",
        "drm_license_uri": "https://static.dplay.tech/imagenes/json/history.json"
      },
      {
        "name": "DISCOVERY",
        "uri": "https://edge-live16-sl.cvattv.com.ar/live/c3eds/DiscoveryHD/SA_Live_dash_enc_2A/DiscoveryHD.mpd",
        "drm_scheme": "clearkey",
        "drm_license_uri": "https://static.dplay.tech/imagenes/json/discovery.json"
      },
      {
        "name": "DISCOVERY H&H",
        "uri": "https://edge-live16-sl.cvattv.com.ar/live/c3eds/DiscoveryHomeHealthHD/SA_Live_dash_enc_2A/DiscoveryHomeHealthHD.mpd",
        "drm_scheme": "clearkey",
        "drm_license_uri": "https://static.dplay.tech/imagenes/json/discoveryhomehealth.json"
      },
      {
        "name": "DISCOVERY ID",
        "uri": "https://edge-live16-sl.cvattv.com.ar/live/c7eds/ID/SA_Live_dash_enc_2A/ID.mpd",
        "drm_scheme": "clearkey",
        "drm_license_uri": "https://static.dplay.tech/imagenes/json/discoveryid.json"
      },
      {
        "name": "DISCOVERY SCIENCE",
        "uri": "https://edge-live16-sl.cvattv.com.ar/live/c6eds/Discovery_Science/SA_Live_dash_enc_2A/Discovery_Science.mpd",
        "drm_scheme": "clearkey",
        "drm_license_uri": "https://static.dplay.tech/imagenes/json/discoveryscience.json"
      },
      {
        "name": "DISCOVERY TURBO",
        "uri": "https://edge-live16-sl.cvattv.com.ar/live/c7eds/DiscoveryTurbo/SA_Live_dash_enc_2A/DiscoveryTurbo.mpd",
        "drm_scheme": "clearkey",
        "drm_license_uri": "https://static.dplay.tech/imagenes/json/discoveryturbo.json"
      },
      {
        "name": "DISCOVERY TURBO",
        "uri": "https://edge-live16-sl.cvattv.com.ar/live/c7eds/DiscoveryTurbo/SA_Live_dash_enc_2A/DiscoveryTurbo.mpd",
        "drm_scheme": "clearkey",
        "drm_license_uri": "https://static.dplay.tech/imagenes/json/discoveryturbo.json"
      },
      {
        "name": "DISCOVERY TEATER",
        "uri": "https://edge-live16-sl.cvattv.com.ar/live/c6eds/Theater_HD/SA_Live_dash_enc_2A/Theater_HD.mpd",
        "drm_scheme": "clearkey",
        "drm_license_uri": "https://static.dplay.tech/imagenes/json/discoverytheather.json"
      },
      {
        "name": "DISCOVERY TLC",
        "uri": "https://edge-live16-sl.cvattv.com.ar/live/c6eds/TLC/SA_Live_dash_enc_2A/TLC.mpd",
        "drm_scheme": "clearkey",
        "drm_license_uri": "https://static.dplay.tech/imagenes/json/discoverytlc.json"
      },
      {
        "name": "DISCOVERY WORL",
        "uri": "https://edge-live16-sl.cvattv.com.ar/live/c6eds/Discovery_World_HD/SA_Live_dash_enc_2A/Discovery_World_HD.mpd",
        "drm_scheme": "clearkey",
        "drm_license_uri": "https://static.dplay.tech/imagenes/json/discoveryworld.json"
      }
    ]
  },
  {
    "name": "PARAGUAY",
    "samples": [
      {
        "name": "TRECE PY",
        "uri": "https://edge-live16-sl.cvattv.com.ar/live/c4eds/RPC_C4/SA_Live_dash_enc_2A/RPC_C4.mpd",
        "drm_scheme": "clearkey",
        "drm_license_uri": "https://static.dplay.tech/imagenes/json/rpc.json"
      },
      {
        "name": "UNICANAL",
        "uri": "https://edge-live16-sl.cvattv.com.ar/live/c4eds/UNICANAL_C4/SA_Live_dash_enc_2A/UNICANAL_C4.mpd",
        "drm_scheme": "clearkey",
        "drm_license_uri": "https://static.dplay.tech/imagenes/json/rpc.json"
      },
      {
        "name": "ABC TV",
        "uri": "https://edge-live16-sl.cvattv.com.ar/live/c5eds/ABC_TV_C4/SA_Live_dash_enc_2A/ABC_TV_C4.mpd",
        "drm_scheme": "clearkey",
        "drm_license_uri": "https://static.dplay.tech/imagenes/json/abctv.json"
      },
      {
        "name": "NPY PY",
        "uri": "https://edge03-cde-py.cvattv.com.ar/live/c4eds/NOTICIAS_PY_C4/SA_Live_dash_enc_2A/NOTICIAS_PY_C4.mpd",
        "drm_scheme": "widevine",
        "drm_license_uri": "https://exoplaydoo.000webhostapp.com/keys/npy.json"
      },
      {
        "name": "TELEFUTURO PY",
        "uri": "https://edge-live16-sl.cvattv.com.ar/live/c4eds/TELEFUTURO_C4/SA_Live_dash_enc_2A/TELEFUTURO_C4.mpd",
        "drm_scheme": "clearkey",
        "drm_license_uri": "https://static.dplay.tech/imagenes/json/telefuturo.json"
      },
      {
        "name": "LA TELE",
        "uri": "https://edge-live16-sl.cvattv.com.ar/live/c4eds/LA_TELE_C4/SA_Live_dash_enc_2A/LA_TELE_C4.mpd",
        "drm_scheme": "clearkey",
        "drm_license_uri": "https://static.dplay.tech/imagenes/json/latele.json"
      },
      {
        "name": "C9N",
        "uri": "https://edge01-cde-py.cvattv.com.ar/live/c5eds/C9N_C4/SA_Live_dash_enc_2A/C9N_C4.mpd",
        "drm_scheme": "clearkey",
        "drm_license_uri": "https://exoplaydoo.000webhostapp.com/keys/c9n.json"
      },
      {
        "name": "PARAVISION",
        "uri": "https://edge-live16-sl.cvattv.com.ar/live/c4eds/PARAVISION_C4/SA_Live_dash_enc_2A/PARAVISION_C4.mpd",
        "drm_scheme": "clearkey",
        "drm_license_uri": "https://static.dplay.tech/imagenes/json/paravision.json"
      },
      {
        "name": "SNT",
        "uri": "https://edge-live16-sl.cvattv.com.ar/live/c4eds/SNT_C4/SA_Live_dash_enc_2A/SNT_C4.mpd",
        "drm_scheme": "clearkey",
        "drm_license_uri": "https://static.dplay.tech/imagenes/json/snt.json"
      },
      {
        "name": "GEN TV",
        "uri": "https://edge-live16-sl.cvattv.com.ar/live/c7eds/GEN_TV/SA_Live_dash_enc_2A/GEN_TV.mpd",
        "drm_scheme": "clearkey",
        "drm_license_uri": "https://static.dplay.tech/imagenes/json/gentv.json"
      },
      {
        "name": "SUR TV",
        "uri": "https://edge-live16-sl.cvattv.com.ar/live/c4eds/SUR_TV_C4/SA_Live_dash_enc_2A/SUR_TV_C4.mpd",
        "drm_scheme": "clearkey",
        "drm_license_uri": "https://static.dplay.tech/imagenes/json/sur.json"
      },
      {
        "name": "CANAL PRO",
        "uri": "https://edge-live16-sl.cvattv.com.ar/live/c7eds/Canal_PRO/SA_Live_dash_enc_2A/Canal_PRO.mpd",
        "drm_scheme": "clearkey",
        "drm_license_uri": "https://static.dplay.tech/imagenes/json/pro.json"
      },
      {
        "name": "5 DIAS PY",
        "uri": "https://edge-live16-sl.cvattv.com.ar/live/c4eds/5_Dias_PY/SA_Live_dash_enc_2A/5_Dias_PY.mpd",
        "drm_scheme": "clearkey",
        "drm_license_uri": "https://static.dplay.tech/imagenes/json/5dias.json"
      },
      {
        "name": "PY TV",
        "uri": "https://edge-live16-sl.cvattv.com.ar/live/c7eds/Paraguay_TV/SA_Live_dash_enc_2A/Paraguay_TV.mpd",
        "drm_scheme": "clearkey",
        "drm_license_uri": "https://static.dplay.tech/imagenes/json/paraguaytv.json"
      },
      {
        "name": "TV CÁMARA",
        "uri": "https://edge-live16-sl.cvattv.com.ar/live/c4eds/TV_Camara/SA_Live_dash_enc_2A/TV_Camara.mpd",
        "drm_scheme": "clearkey",
        "drm_license_uri": "https://static.dplay.tech/imagenes/json/tvcamara.json"
      }
    ]
  },
  {
    "name": "INFANTILES",
    "samples": [
      {
        "name": "CARTONCITO",
        "uri": "https://edge-live16-sl.cvattv.com.ar/live/c7eds/Boomerang/SA_Live_dash_enc_2A/Boomerang.mpd",
        "drm_scheme": "clearkey",
        "drm_license_uri": "https://static.dplay.tech/imagenes/json/cartoonito.json"
      },
      {
        "name": "CARTOON NETWORT",
        "uri": "https://edge-live16-sl.cvattv.com.ar/live/c3eds/CartoonNetwork/SA_Live_dash_enc_2A/CartoonNetwork.mpd",
        "drm_scheme": "clearkey",
        "drm_license_uri": "https://static.dplay.tech/imagenes/json/cartoonetwork.json"
      },
      {
        "name": "DISCOVERY KIDS",
        "uri": "https://edge-live16-sl.cvattv.com.ar/live/c6eds/Discovery_Kids/SA_Live_dash_enc_2A/Discovery_Kids.mpd",
        "drm_scheme": "clearkey",
        "drm_license_uri": "https://static.dplay.tech/imagenes/json/discoverykid.json"
      }
    ]
  },
  {
    "name": "DEPORTES",
    "samples": [
      {
        "name": "ESPN",
        "uri": "https://edge-live16-sl.cvattv.com.ar/live/c3eds/ESPN2HD/SA_Live_dash_enc_2A/ESPN2HD.mpd",
        "drm_scheme": "clearkey",
        "drm_license_uri": "https://exoplaydoo.000webhostapp.com/keys/espn1.json"
      },
      {
        "name": "ESPN 2",
        "uri": "https://edge-live16-sl.cvattv.com.ar/live/c6eds/ESPN2_Arg/SA_Live_dash_enc_2A/ESPN2_Arg.mpd",
        "drm_scheme": "clearkey",
        "drm_license_uri": "https://static.dplay.tech/imagenes/json/espn2.json"
      },
      {
        "name": "ESPN 3",
        "uri": "https://edge-live16-sl.cvattv.com.ar/live/c3eds/ESPN3/SA_Live_dash_enc_2A/ESPN3.mpd",
        "drm_scheme": "clearkey",
        "drm_license_uri": "https://static.dplay.tech/imagenes/json/espn3.json"
      },
      {
        "name": "ESPN XTRA",
        "uri": "https://edge-live16-sl.cvattv.com.ar/live/c3eds/ESPNHD/SA_Live_dash_enc_2A/ESPNHD.mpd",
        "drm_scheme": "clearkey",
        "drm_license_uri": "https://static.dplay.tech/imagenes/json/espnextra.json"
      },
      {
        "name": "TAE KWON DOO",
        "uri": "https://srv6.zcast.com.br/tkd/tkd/playlist.m3u8"
      },
      {
        "name": "FOX SPORTS 1",
        "uri": "https://edge-live16-sl.cvattv.com.ar/live/c3eds/FoxSports/SA_Live_dash_enc_2A/FoxSports.mpd",
        "drm_scheme": "clearkey",
        "drm_license_uri": "https://static.dplay.tech/imagenes/json/foxsport.json"
      },
      {
        "name": "FOX SPORTS 2",
        "uri": "https://edge-live16-sl.cvattv.com.ar/live/c3eds/FoxSports2HD/SA_Live_dash_enc_2A/FoxSports2HD.mpd",
        "drm_scheme": "clearkey",
        "drm_license_uri": "https://static.dplay.tech/imagenes/json/foxsport2.json"
      },
      {
        "name": "FOX SPORTS 3",
        "uri": "https://edge-live16-sl.cvattv.com.ar/live/c3eds/FoxSports3HD/SA_Live_dash_enc_2A/FoxSports3HD.mpd",
        "drm_scheme": "clearkey",
        "drm_license_uri": "https://static.dplay.tech/imagenes/json/foxsport3.json"
      },
      {
        "name": "TYC SPORTS",
        "uri": "https://edge-live16-sl.cvattv.com.ar/live/c7eds/TyCSport/SA_Live_dash_enc/TyCSport.mpd",
        "drm_scheme": "clearkey",
        "drm_license_uri": "https://static.dplay.tech/imagenes/json/tycsport.json"
      },
      {
        "name": "DEPORTV",
        "uri": "https://edge-live16-sl.cvattv.com.ar/live/c3eds/DeporTVHD/SA_Live_dash_enc_2A/DeporTVHD.mpd",
        "drm_scheme": "clearkey",
        "drm_license_uri": "https://static.dplay.tech/imagenes/json/deportv.json"
      },
      {
        "name": "GARAGE TV",
        "uri": "https://edge-live16-sl.cvattv.com.ar/live/c6eds/El_Garage/SA_Live_dash_enc_2A/El_Garage.mpd",
        "drm_scheme": "clearkey",
        "drm_license_uri": "https://static.dplay.tech/imagenes/json/garagetv.json"
      },
      {
        "name": "GOLF CHANNEL",
        "uri": "https://edge-live16-sl.cvattv.com.ar/live/c6eds/Golf_Channel/SA_Live_dash_enc_2A/Golf_Channel.mpd",
        "drm_scheme": "clearkey",
        "drm_license_uri": "https://static.dplay.tech/imagenes/json/golf.json"
      },
      {
        "name": "NBA",
        "uri": "https://edge-live16-sl.cvattv.com.ar/live/c6eds/NBA_TV/SA_Live_dash_enc_2A/NBA_TV.mpd",
        "drm_scheme": "clearkey",
        "drm_license_uri": "https://static.dplay.tech/imagenes/json/nba.json"
      },
      {
        "name": "AMERICA SPORTS",
        "uri": "https://edge-live16-sl.cvattv.com.ar/live/c6eds/America_Sports/SA_Live_dash_enc_2A/America_Sports.mpd",
        "drm_scheme": "clearkey",
        "drm_license_uri": "https://static.dplay.tech/imagenes/json/americasport.json"
      },
      {
        "name": "PX SPORT",
        "uri": "https://edge-live16-sl.cvattv.com.ar/live/c7eds/PX_Sports/SA_Live_dash_enc_2A/PX_Sports.mpd",
        "drm_scheme": "clearkey",
        "drm_license_uri": "https://static.dplay.tech/imagenes/json/pxsport.json"
      },
      {
        "name": "DEPORTV",
        "uri": "https://edge-live16-sl.cvattv.com.ar/live/c3eds/DeporTVHD/SA_Live_dash_enc_2A/DeporTVHD.mpd",
        "drm_scheme": "clearkey",
        "drm_license_uri": "https://static.dplay.tech/imagenes/json/deportv.json"
      },
      {
        "name": "TNT SPORT HD",
        "uri": "https://edge-live16-sl.cvattv.com.ar/live/c6eds/TNT_Sports_HD/SA_Live_dash_enc_2A/TNT_Sports_HD.mpd",
        "drm_scheme": "clearkey",
        "drm_license_uri": "https://exoplaydoo.000webhostapp.com/keys/tntsporthd.json"
      },
      {
        "name": "DIRECTV COLOMBIA",
        "uri": "https://dtvott-cbc.akamaized.net/dash_live_1060/manifest.mpd",
        "drm_scheme": "clearkey",
        "drm_license_uri": "https://exoplaydoo.000webhostapp.com/keys/directvcolo.json"
      },
      {
        "name": "DIRECTV 2",
        "uri": "http://179.41.1.86/exec/ch2_bak.mpd",
        "drm_scheme": "clearkey",
        "drm_license_uri": "https://exoplaydoo.000webhostapp.com/keys/dtv2.json"
      },
      {
        "name": "DIRECTV +",
        "uri": "https://dtvott-abc.akamaized.net/dash_live_1071/manifest.mpd",
        "drm_scheme": "clearkey",
        "drm_license_uri": "https://exoplaydoo.000webhostapp.com/keys/dtv+.json"
      }
    ]
  },
  {
    "name": "DAZN",
    "samples": [
      {
        "name": "DAZN ALEMANIA",
        "uri" : "https://dce-ak-livewwdazn.akamaized.net/dashdrm/dazn-linear-017/stream.mpd?p=web",
        "drm_scheme": "clearkey",
        "drm_license_uri": "https://exoplaydoo.000webhostapp.com/keys/daznnes.json"  
      },
      {
        "name": "DAZN ALEMANIA 2",
        "uri" : "https://dce-ak-livewwdazn.akamaized.net/dashdrm/dazn-linear-018/stream.mpd?p=web",
        "drm_scheme": "clearkey",
        "drm_license_uri": "https://exoplaydoo.000webhostapp.com/keys/daznnes.json"  
      },
      {
        "name": "DAZN ESPAÑA 1",
        "uri" : "https://dce-ak-livewwdazn.akamaized.net/dashdrm/dazn-linear-037/stream.mpd?p=web",
        "drm_scheme": "clearkey",
        "drm_license_uri": "https://exoplaydoo.000webhostapp.com/keys/daznnes.json"  
      },
      {
        "name": "DAZN ESPAÑA 2",
        "uri" : "https://dce-ak-livewwdazn.akamaized.net/dashdrm/dazn-linear-038/stream.mpd?p=web",
        "drm_scheme": "clearkey",
        "drm_license_uri": "https://exoplaydoo.000webhostapp.com/keys/daznnes.json"  
      },
      {
        "name": "DAZN FORMULA 1",
        "uri" : "https://dce-ak-livewwdazn.akamaized.net/dashdrm/dazn-linear-016/stream.mpd?p=web",
        "drm_scheme": "clearkey",
        "drm_license_uri": "https://exoplaydoo.000webhostapp.com/keys/daznnes.json"  
      },
      {
        "name": "DAZN LA LIGA",
        "uri" : "https://dce-ak-livewwdazn.akamaized.net/dashdrm/dazn-linear-043/stream.mpd?p=web",
        "drm_scheme": "clearkey",
        "drm_license_uri": "https://exoplaydoo.000webhostapp.com/keys/daznnes.json"  
      },
      {
        "name": "VIX A",
        "uri" : "https://dcs3-live-ue1.mp.lura.live/server/play/0MqnqghkvXVNIEm0/manifest.mpd?anvsid=m176963355-n3affb8d43b72f1268220bf2f218069e8",
        "drm_scheme": "widevine",
        "drm_license_uri": "https://drm3.mp.lura.live/cenc?eqp=HAB2CMh0lU8z7E9r0QMWHcIf49hXgacr29Codk2r6WBtOByNij0LsjRzB9bzM14YzaHYIX-DbpK2uya1MQaYettkhYfeywSDoXZnHjYFdu3ZiLLEuQhnkLimr3V6tNN-xxr5Kk1h6jBpbNXmem3BAWO4ufyVk2C7xBnBHMHoEODw2ZHqZKqh_wfX7sJjnMgxBrKZUB0H8F8E_v_9FV7u5b3rM7BX8DejUSdfcVfDRkTRSCP9LizZVqRql87lOi8m0EV3i1Iq4M3dO3drbKmKa9DkkKktvSLOlHELrBXCNzMfGbFRxFgIsPatvE28Eqzi&anvauth=tb=0~te=1684250136~sgn=be6acf76c858cb8c00e4f53ab5436849bc96ba2d44a928e107c45687b44f73d6&t=1684239336&guid=0e7d9696-a033-91da-ce76313698ac"  
      }
    ]
  },
  {
    "name": "INTERNACIONALES",
    "samples": [
      {
        "name": "A SON DE SALSA",
        "uri": "https://cloud01.mipaneltv.xyz/asondesalsa/asondesalsa/playlist.m3u8"
      },
      {
        "name": "Music 88 Stereo",
        "uri": "https://k3.usastreams.com/CableLatino/88stereo/playlist.m3u8"
      },
      {
        "name": "Tele Antequera",
        "uri": "https://limited38.todostreaming.es/live/101tv-AntequeraHD.m3u8"
      },
      {
        "name": "Alfa & Omega Visión",
        "uri": "https://srv.panelcast.net/aovision/aovision/playlist.m3u8"
      },
      {
        "name": "Alsacias TV",
        "uri": "https://emisoras.hn:8081/atv/index.m3u8"
      },
      {
        "name": "Aliento Vision",
        "uri": "http://209.133.209.195:1935/AlientoSD/smil:AlientoSD.smil/playlist.m3u8"
      },
      {
        "name": "AlmayaTV",
        "uri": "https://59ce1298bfb98.streamlock.net/almayatv/almayatv/playlist.m3u8"
      },

      {
        "name": "Alternativa TV",
        "uri": "https://srv2.zcast.com.br/carlos2469/carlos2469/playlist.m3u8"
      },
      {
        "name": "AMC East",
        "uri": "https://bcovlive-a.akamaihd.net/b3ed62003de946c896f4f541b908376e/us-east-1/6240731308001/playlist.m3u8"
      },
      {
        "name": "AMX Noticias",
        "uri": "https://5e50264bd6766.streamlock.net/mexiquense2/videomexiquense2/playlist.m3u8"
      },
      {
        "name": "ANDES TV",
        "uri": "https://stmv1.voxhdnet.com/tvsicuani/tvsicuani/playlist.m3u8"
      },
      {
        "name": "Antena 91",
        "uri": "https://tuvideoonline.com.ar:3393/live/antena91live.m3u8"
      },
      {
        "name": "Antofagasta TV",
        "uri": "https://unlimited6-cl.dps.live/atv/atv.smil/playlist.m3u8"
      },
      {
        "name": "Anzoátegui TV",
        "uri": "https://vcp2.myplaytv.com/anzoateguitv/anzoateguitv/playlist.m3u8https://593b04c4c5670.streamlock.net/8192/8192/playlist.m3u8"
      },
      {
        "name": "Aragón TV",
        "uri": "https://cartv.streaming.aranova.es/hls/live/aragontv_canal1.m3u8"
      },
      {
        "name": "AsiriTV",
        "uri": "https://video2.lhdserver.es/asiritv/live.m3u8"
      },
      {
        "name": "Asomavisión",
        "uri": "https://asomatv.duckdns.org/livestream/stream.m3u8"
      },
      {
        "name": "Atacama TV",
        "uri": "https://v2.tustreaming.cl/atacamatv/index.m3u8"
      },
      {
        "name": "ATN Televisión",
        "uri": "https://59ef525c24caa.streamlock.net/atntelevision/atntelevision/playlist.m3u8"
      },
      {
        "name": "ATV+ Noticias",
        "uri": "https://dysmuyxh5vstv.cloudfront.net/hls/atv2.m3u8"
      },
      {
        "name": "Auténtica Televisión",
        "uri": "https://live.obslivestream.com/autenticatvmux/index.m3u8"
      },
      {
        "name": "Avivamiento TV",
        "uri": "https://s1.abntelevision.com/avivamientoabr/stream/avivamientohd/avivamientohd/playlist.m3u8"
      },
      {
        "name": "AZM TV",
        "uri": "https://live.canalnueve.tv/canal.m3u8"
      },
      {
        "name": "Bailén TV",
        "uri": "http://cpd.bailen.tv:8080/Playlist_CANAL_24H/playlist.m3u8"
      },
      {
        "name": "Bajo Techo TV",
        "uri": "https://cdn4.hostlagarto.com:8081/static/bajotechotv/playlist.m3u8"
      },
      {
        "name": "Bayres TV",
        "uri": "https://streaming02.gbasat.com.ar:19360/bayrestv/bayrestv.m3u8"
      },
      {
        "name": "BBC America",
        "uri": "https://bcovlive-a.akamaihd.net/c9bf201b06694453bb29282f97191f58/us-east-1/6240731308001/playlist.m3u8"
      },
      {
        "name": "Beats Radio",
        "uri": "https://59537faa0729a.streamlock.net/beatsradio/beatsradio/playlist.m3u8"
      },
      {
        "name": "Bella Asuncion TV",
        "uri": "https://tvdatta.com:3602/stream/play.m3u8"
      },
      {
        "name": "Best Cable Más Cumbia",
        "uri": "https://tv.inka.net.pe/mascumbiatvonline/mascumbiatvonline/index.m3u8"
      },
      {
        "name": "Best Cable Perú",
        "uri": "https://tv.inka.net.pe/bestcable/bestcable/index.m3u8"
      },
      {
        "name": "Best Cable Sports Perú",
        "uri": "https://tv.inka.net.pe/bestcablesports/bestcablesports/index.m3u8"
      },
      {
        "name": "Bethel TV",
        "uri": "https://ott.streann.com/loadbalancer/services/public/channels/5e0689c82cdcb4fdbcd79151/playlist.m3u8"
      },
      {
        "name": "Beverly Hills Television 10",
        "uri": "https://cdn3.wowza.com/5/V2Y2VmhqMEFDTUkx/beverlyhills/G0072_006/playlist.m3u8"
      },
      {
        "name": "Beverly Hills Television 35",
        "uri": "https://cdn3.wowza.com/5/V2Y2VmhqMEFDTUkx/beverlyhills/G0072_007/playlist.m3u8"
      },
      {
        "name": "BHTV",
        "uri": "http://cdn1.ujjina.com:1935/iptvbhtv/livebhtvtv/playlist.m3u8"
      },
      {
        "name": "Bolivia TV 7.2",
        "uri": "https://video1.getstreamhosting.com:1936/8224/8224/playlist.m3u8"
      },
      {
        "name": "Bolivia TV 7.2 Deportes",
        "uri": "https://5ca3e84a76d30.streamlock.net/boliviatv2/videoboliviatv2/playlist.m3u8"
      },
      {
        "name": "Bolivia TV",
        "uri": "http://boliviatv1.srfms.com:5735/live/livestream/playlist.m3u8"
      },
      {
        "name": "Bolivisión",
        "uri": "https://d2byzrnrdb259r.cloudfront.net/hls/live.m3u8"
      },
      {
        "name": "Bonao TV",
        "uri": "https://ss5.domint.net:3026/btv_str/bonao/playlist.m3u8"
      },
      {
        "name": "Buenísima Radio TV",
        "uri": "https://streamyes.alsolnet.com/buturama/live/playlist.m3u8"
      },
      {
        "name": "Buin Somos Todos",
        "uri": "https://bst.buin.cl/0.m3u8"
      },
      {
        "name": "BVC",
        "uri": "https://vivo.solumedia.com:19360/bvconline/bvconline.m3u8"
      },
      {
        "name": "C9N",
        "uri": "https://d4xunn272arip.cloudfront.net/hls/c9n.m3u8"
      },
      {
        "name": "C20 Canal 20 Villa María",
        "uri": "https://cronos.aldeaglobal.net.ar/hls/canal20.m3u8"
      },
      {
        "name": "Cabina RPC Radio",
        "uri": "https://mdstrm.com/live-stream-playlist/5d976689ab55a60f94ec98e8.m3u8"
      },
      {
        "name": "Cabina Telemetro Radio",
        "uri": "https://mdstrm.com/live-stream-playlist/5d97ca5673de440761ff194e.m3u8"
      } 
    ] 
  } 
]
